LICENSE
README.md
setup.py
pysaber/__init__.py
pysaber/saberio.py
pysaber/utils/__init__.py
pysaber/utils/helpers.py
saberio.egg-info/PKG-INFO
saberio.egg-info/SOURCES.txt
saberio.egg-info/dependency_links.txt
saberio.egg-info/entry_points.txt
saberio.egg-info/requires.txt
saberio.egg-info/top_level.txt