Metadata-Version: 2.1
Name: saberio
Version: 1.0.1
Summary: A python module to download song for Beat Saber
Home-page: https://github.com/mortafix/PySaber
Author: Moris Doratiotto
Author-email: moris.doratiotto@gmail.com
Keywords: beat saber,bsaber,beat saver
Classifier: Programming Language :: Python :: 3.8
Classifier: License :: OSI Approved :: MIT License
Classifier: Operating System :: OS Independent
Classifier: Development Status :: 3 - Alpha
Classifier: Intended Audience :: Developers
Requires-Python: >=3.8
License-File: LICENSE
